nux/__init__.py
nux/util.py
nux/flows/__init__.py
nux/flows/base.py
nux/flows/compose.py
nux/flows/priors.py
nux/flows/bijective/__init__.py
nux/flows/bijective/affine.py
nux/flows/bijective/conv.py
nux/flows/bijective/coupling.py
nux/flows/bijective/igr.py
nux/flows/bijective/maf.py
nux/flows/bijective/mixture_cdf.py
nux/flows/bijective/nonlinearities.py
nux/flows/bijective/normalization.py
nux/flows/bijective/reshape.py
nux/flows/bijective/spline.py
nux/flows/injective/__init__.py
nux/flows/injective/importance_weighted.py
nux/flows/injective/nif.py
nux/flows/injective/upsample_nif.py
nux/flows/surjective/__init__.py
nux/flows/surjective/dequantize.py
nux/tests/__init__.py
nux/tests/nf_test.py
nux/tests/nif_test.py
nux-1.0.3.dist-info/METADATA
nux-1.0.3.dist-info/WHEEL
nux-1.0.3.dist-info/top_level.txt
nux-1.0.3.dist-info/RECORD
