Metadata-Version: 2.1
Name: nux
Version: 1.0.3
Summary: Normalizing Flows using Jax
Home-page: https://github.com/Information-Fusion-Lab-Umass/NuX
Author: Information Fusion Lab
Author-email: rzabounidis@cs.umass.edu
License: UNKNOWN
Platform: UNKNOWN
Classifier: Programming Language :: Python :: 3
Classifier: License :: OSI Approved :: MIT License
Classifier: Operating System :: OS Independent
Requires-Python: >=3.6
Requires-Dist: numpy (>=1.12)
Requires-Dist: jax
Requires-Dist: jaxlib
